clearml_agent_bootstrap/__init__.py
clearml_agent_bootstrap/version.py
clearml_agent_bootstrap-0.0.0.dist-info/METADATA
clearml_agent_bootstrap-0.0.0.dist-info/WHEEL
clearml_agent_bootstrap-0.0.0.dist-info/top_level.txt
clearml_agent_bootstrap-0.0.0.dist-info/RECORD
